ml_adapter/numpy/__init__.py
ml_adapter/numpy/adapter.py
ml_adapter/numpy/marshall.py
ml_adapter/numpy/py.typed
waylay_ml_adapter_numpy-0.1.1.dist-info/licenses/LICENCE.txt
waylay_ml_adapter_numpy-0.1.1.dist-info/METADATA
waylay_ml_adapter_numpy-0.1.1.dist-info/WHEEL
waylay_ml_adapter_numpy-0.1.1.dist-info/top_level.txt
waylay_ml_adapter_numpy-0.1.1.dist-info/RECORD
