Metadata-Version: 2.4
Name: waylay-ml-adapter-numpy
Version: 0.1.1
Summary: ML_adapter for numpy.
Author-email: Waylay <info@waylay.io>
Requires-Python: >=3.11
License-File: LICENCE.txt
Requires-Dist: numpy>=1.25.0
Requires-Dist: waylay-ml-adapter-base
Provides-Extra: dev
Requires-Dist: waylay-ml-adapter-devtools; extra == "dev"
Dynamic: license-file
